Metadata-Version: 2.1
Name: rop
Version: 0.0.1
Summary: Rigid-body Object Perception: automatic production detection/instance segmentation/counting/6d pose algorithm by combining 3D reconstruction and synthetic data.
Home-page: https://github.com/DIYer22/rop
Author: DIYer22
Author-email: ylxx@live.com
License: UNKNOWN
Platform: UNKNOWN
Classifier: Topic :: Software Development :: Libraries :: Python Modules
Classifier: Programming Language :: Python :: 3
Classifier: License :: OSI Approved :: MIT License
Classifier: Operating System :: OS Independent
